cmk_tools/__init__.py
cmk_tools/call_test_server.py
cmk_tools/elk_client.py
cmk_tools/locals.py
cmk_tools/logger.py
cmk_tools/mkp_packer.py
cmk_tools/redis_semaphore.py
cmk_tools/rest_request.py
cmk_tools/rest_request_v2.py
cmk_tools/snmp_client.py
cmk_tools/status.py
cmk_tools/utils.py
cmk_tools-2.1.2.dist-info/METADATA
cmk_tools-2.1.2.dist-info/WHEEL
cmk_tools-2.1.2.dist-info/RECORD
