Metadata-Version: 2.3
Name: cmk-tools
Version: 2.1.2
Summary: 
Author: NhanDD3
Author-email: nhandd3@fpt.com
Requires-Python: >=3.8,<4.0
Classifier: Programming Language :: Python :: 3
Classifier: Programming Language :: Python :: 3.8
Classifier: Programming Language :: Python :: 3.9
Classifier: Programming Language :: Python :: 3.10
Classifier: Programming Language :: Python :: 3.11
Classifier: Programming Language :: Python :: 3.12
Classifier: Programming Language :: Python :: 3.13
Requires-Dist: bump2version (>=1.0.1,<2.0.0)
Requires-Dist: elasticsearch (==7.14.0)
Requires-Dist: pytest (>=8.3.3,<9.0.0)
Requires-Dist: python-json-logger (>=2.0.7,<3.0.0)
Requires-Dist: redis (>=5.1.1,<6.0.0)
Requires-Dist: requests (>=2.32.3,<3.0.0)
